BearFramework-1.1.0.dist-info/DESCRIPTION.rst
BearFramework-1.1.0.dist-info/METADATA
BearFramework-1.1.0.dist-info/RECORD
BearFramework-1.1.0.dist-info/WHEEL
BearFramework-1.1.0.dist-info/metadata.json
BearFramework-1.1.0.dist-info/top_level.txt
bear/RunUnittest.py
bear/SkiCommonData.py
bear/__init__.py
bear/base.py
bear/install_data.py
bear/log/__init__.py
bear/log/logger.py
