Metadata-Version: 2.0
Name: BearFramework
Version: 1.1.0
Summary: this is my TestFramework
Home-page: https://www.agavetest.info
Author: sirius
Author-email: UNKNOWN
License: MIT
Platform: UNKNOWN
